README.md
setup.py
raptorlink/__init__.py
raptorlink/raptorlink.py
raptorlink.egg-info/PKG-INFO
raptorlink.egg-info/SOURCES.txt
raptorlink.egg-info/dependency_links.txt
raptorlink.egg-info/entry_points.txt
raptorlink.egg-info/top_level.txt