Metadata-Version: 1.0
Name: raptorlink
Version: 0.2.0
Summary: test plugins for submit test result to raptor server based on nosetests
Home-page: UNKNOWN
Author: liuchengtao
Author-email: chengtao.liu@yahoo.com
License: MIT
Platform: UNKNOWN
